dipamkara/__init__.py
dipamkara/const.py
dipamkara/dipamkara.py
dipamkara/dipamkara_dsl.py
dipamkara/lock.py
dipamkara/logger.py
dipamkara/util.py
dipamkara/decorator/__init__.py
dipamkara/decorator/lock_on.py
dipamkara/embedding/__init__.py
dipamkara/embedding/distance.py
dipamkara/embedding/metric.py
dipamkara/embedding/normalize.py
dipamkara/exception/__init__.py
dipamkara/exception/dipamkara_dimension_error.py
dipamkara/exception/dipamkara_index_error.py
dipamkara/exception/dipamkara_index_existence_error.py
dipamkara/exception/dipamkara_metric_not_support_error.py
dipamkara/exception/dipamkara_syntax_error.py
dipamkara/exception/dipamkara_vector_error.py
dipamkara/exception/dipamkara_vector_existence_error.py
test/__init__.py
test/test.py
dipamkara-0.3.9.dist-info/LICENSE
dipamkara-0.3.9.dist-info/METADATA
dipamkara-0.3.9.dist-info/WHEEL
dipamkara-0.3.9.dist-info/top_level.txt
dipamkara-0.3.9.dist-info/RECORD
