Metadata-Version: 2.1
Name: dipamkara
Version: 0.3.9
Summary: A light-weight vector database engine.
Home-page: https://github.com/vortezwohl/Dipamkara
Author: vortezwohl
Author-email: vortez.wohl@gmail.com
License: GNU GENERAL PUBLIC LICENSE
Project-URL: Bug Tracker, https://github.com/vortezwohl/Dipamkara/issues
Classifier: Programming Language :: Python :: 3
Classifier: Operating System :: OS Independent
Classifier: Natural Language :: English
Requires-Python: >=3.10
License-File: LICENSE
Requires-Dist: numpy
